LICENSE
MANIFEST.in
README.md
package.json
setup.py
designable_radio_items/DesignableRadioItems.py
designable_radio_items/__init__.py
designable_radio_items/_imports_.py
designable_radio_items/designable_radio_items.min.js
designable_radio_items/designable_radio_items.min.js.map
designable_radio_items/metadata.json
designable_radio_items/package-info.json
designable_radio_items.egg-info/PKG-INFO
designable_radio_items.egg-info/SOURCES.txt
designable_radio_items.egg-info/dependency_links.txt
designable_radio_items.egg-info/top_level.txt