Metadata-Version: 2.1
Name: designable-radio-items
Version: 1.1.15
Summary: Dash Designable Radio Items
Author: s_matsumoto <s_matsumoto@thinkup-sol.co.jp>
License: MIT
Classifier: Framework :: Dash
License-File: LICENSE
